aplicaciones.py
aplicaciones-1.0.data/scripts/aplicaciones.py
aplicaciones-1.0.dist-info/METADATA
aplicaciones-1.0.dist-info/WHEEL
aplicaciones-1.0.dist-info/top_level.txt
aplicaciones-1.0.dist-info/RECORD
