Metadata-Version: 2.4
Name: aplicaciones
Version: 1.0
Summary: Mi instalador de aplicaciones usando setuptools
Home-page: http://apendiendo/python/
Author: Ernesto Castro
License: GPL
Dynamic: author
Dynamic: home-page
Dynamic: license
Dynamic: summary
